{
	"configurations" : 
	[
		{
			"directories" : 
			[
				{
					"build" : ".",
					"jsonFile" : "directory-.-Debug-f5ebdc15457944623624.json",
					"minimumCMakeVersion" : 
					{
						"string" : "3.22"
					},
					"projectIndex" : 0,
					"source" : ".",
					"targetIndexes" : 
					[
						0
					]
				}
			],
			"name" : "Debug",
			"projects" : 
			[
				{
					"directoryIndexes" : 
					[
						0
					],
					"name" : "ayp2_plantilla_tp_grupal_2c2023",
					"targetIndexes" : 
					[
						0
					]
				}
			],
			"targets" : 
			[
				{
					"directoryIndex" : 0,
					"id" : "ayp2_plantilla_tp_grupal_2c2023::@6890427a1f51a3e7e1df",
					"jsonFile" : "target-ayp2_plantilla_tp_grupal_2c2023-Debug-79f0e28f5974b4eb8c29.json",
					"name" : "ayp2_plantilla_tp_grupal_2c2023",
					"projectIndex" : 0
				}
			]
		}
	],
	"kind" : "codemodel",
	"paths" : 
	{
		"build" : "/mnt/c/Users/Roman/Documents/TP-Grupal-AYP2-2C2023/cmake-build-debug",
		"source" : "/mnt/c/Users/Roman/Documents/TP-Grupal-AYP2-2C2023"
	},
	"version" : 
	{
		"major" : 2,
		"minor" : 3
	}
}
